knopka/__init__.py
knopka/adapter.py
knopka/exceptions.py
knopka/library/__init__.py
knopka/library/models.py
knopka/utils/__init__.py
knopka/utils/sessions.py
knopka/utils/transliterate.py
knopka-0.0.1.dist-info/LICENSE
knopka-0.0.1.dist-info/METADATA
knopka-0.0.1.dist-info/WHEEL
knopka-0.0.1.dist-info/RECORD
