Metadata-Version: 2.1
Name: knopka
Version: 0.0.1
Summary: another api client for online accounting knopka.com
Home-page: https://github.com/rdnve/knopka
License: MIT
Keywords: finance,accounting
Author: serje ù
Author-email: pleaseanswermeserjeu@icloud.com
Requires-Python: >=3.11,<4.0
Classifier: Development Status :: 3 - Alpha
Classifier: Environment :: Web Environment
Classifier: Intended Audience :: Developers
Classifier: License :: OSI Approved :: MIT License
Classifier: Natural Language :: English
Classifier: Operating System :: OS Independent
Classifier: Programming Language :: Python :: 3
Classifier: Programming Language :: Python :: 3.11
Classifier: Programming Language :: Python :: 3.12
Classifier: Topic :: Internet :: WWW/HTTP
Classifier: Topic :: Software Development :: Libraries
Requires-Dist: attrs (>=23.2,<23.3)
Requires-Dist: requests[socks] (>=2.32,<2.33)
Project-URL: Repository, https://github.com/rdnve/knopka
